[
    {
        "Action": "s3:ListBucketVersions",
        "Resource": "arn:aws:s3:::singlecomm.recordings"
    },
    {
        "Action": "s3:ListBucket",
        "Resource": "arn:aws:s3:::singlecomm.recordings"
    },
{"Action": "s3:GetObject","Resource": "arn:aws:s3:::singlecomm.recordings/0001/584-a/info"},
{"Action": "s3:GetObject","Resource": "arn:aws:s3:::singlecomm.recordings/0001/584-a/lib"},
{"Action": "s3:GetObject","Resource": "arn:aws:s3:::singlecomm.recordings/0001/584-b/etc"},
{"Action": "s3:GetObject","Resource": "arn:aws:s3:::singlecomm.recordings/0001/584-b/tmp"},
{"Action": "s3:GetObject","Resource": "arn:aws:s3:::singlecomm.recordings/0001/584-c/log"},
{"Action": "s3:GetObject","Resource": "arn:aws:s3:::singlecomm.recordings/0001/584-d/mailbox"},
{"Action": "s3:GetObject","Resource": "arn:aws:s3:::singlecomm.recordings/0001/584-e/schedule"},
{"Action": "s3:GetObject","Resource": "arn:aws:s3:::singlecomm.recordings/0001/584-x/doctrine"},
{"Action": "s3:GetObject","Resource": "arn:aws:s3:::singlecomm.recordings/0001/584-a0/foods"},
{"Action": "s3:GetObject","Resource": "arn:aws:s3:::singlecomm.recordings/0001/584-zzz/conclusion"}
]